{
  "info": {
    "description": "data",
    "version": "1.0",
    "year": 2025,
    "contributor": "search engine",
    "source": "augmented",
    "license": {
      "name": "Creative Commons Attribution 4.0 International",
      "url": "https://creativecommons.org/licenses/by/4.0/"
    }
  },
  "images": [
    {
      "id": 7287032642,
      "width": 512,
      "height": 512,
      "file_name": "85l.jpg",
      "size": 131732,
      "format": "JPEG",
      "url": "",
      "hash": "",
      "status": "success"
    }
  ],
  "annotations": [
    {
      "id": 320742642,
      "image_id": 7287032642,
      "category_id": 587,
      "segmentation": [],
      "area": 262144,
      "bbox": [
        0,
        0,
        512,
        512
      ]
    }
  ],
  "categories": [
    {
      "id": 587,
      "name": "Leaf Crinckle 150",
      "supercategory": "blackgram_plant_leaf_disease"
    }
  ]
}